yencryption/__init__.py
yencryption/core.py
yencryption-0.0.2.dist-info/METADATA
yencryption-0.0.2.dist-info/WHEEL
yencryption-0.0.2.dist-info/top_level.txt
yencryption-0.0.2.dist-info/RECORD
