Metadata-Version: 2.4
Name: yencryption
Version: 0.0.2
Summary: Decrypt and Encrypt Easy and secure!
Author-email: SH_Dev <sh-dev@luna-tools.store>
License: MIT
Requires-Python: >=3.7
